shbin.py
shbin-0.3.0.dist-info/entry_points.txt
shbin-0.3.0.dist-info/WHEEL
shbin-0.3.0.dist-info/METADATA
shbin-0.3.0.dist-info/RECORD
