Metadata-Version: 2.1
Name: shbin
Version: 0.3.0
Summary: Turns a Github repo into a pastebin.
Author-email: Alvar Maciel <alvar.maciel@shiphero.com>, Martín Gaitán <marting@shiphero.com>
Requires-Python: >=3.8
Classifier: Programming Language :: Python :: 3
Classifier: Development Status :: 4 - Beta
Classifier: Environment :: Console
Classifier: Intended Audience :: Developers
Classifier: License :: OSI Approved :: BSD License
Classifier: Topic :: Communications :: File Sharing
Requires-Dist: pygithub >= 1.55
Requires-Dist: pyclip >= 0.7.0
Requires-Dist: python-magic >= 0.4.27
Requires-Dist: docopt-ng >= 0.8.1
Requires-Dist: rich >= 12.5
Requires-Dist: pytest ; extra == "dev"
Requires-Dist: black ; extra == "dev"
Project-URL: Changelog, https://github.com/Shiphero/shbin/main/CHANGELOG.md
Project-URL: Home, https://github.com/Shiphero/shbin
Provides-Extra: dev
